Metadata-Version: 2.1
Name: numerix
Version: 1.0.0
Summary: A simple Python library for basic mathematical operations
Home-page: 
License: MIT
